django_export_celery/__init__.py
django_export_celery/admin.py
django_export_celery/apps.py
django_export_celery/forms.py
django_export_celery/mixins.py
django_export_celery/models.py
django_export_celery/resources.py
django_export_celery/statuses.py
django_export_celery/tasks.py
django_export_celery/urls.py
django_export_celery/views.py
django_export_celery/migrations/0001_initial.py
django_export_celery/migrations/0002_auto_20220104_1450.py
django_export_celery/migrations/__init__.py
django_export_celery/tests/__init__.py
django_export_celery/tests/tests.py
django_export_celery-0.3.2.dist-info/LICENSE
django_export_celery-0.3.2.dist-info/METADATA
django_export_celery-0.3.2.dist-info/WHEEL
django_export_celery-0.3.2.dist-info/top_level.txt
django_export_celery-0.3.2.dist-info/RECORD
