Metadata-Version: 2.1
Name: django-export-celery
Version: 0.3.2
Summary: UNKNOWN
Home-page: https://github.com/mrtoffou/django-export-celery
License: UNKNOWN
Platform: UNKNOWN
Classifier: Intended Audience :: Developers
Classifier: Development Status :: 4 - Beta
Classifier: Programming Language :: Python :: 3.6
Classifier: Programming Language :: Python :: 3.7
Classifier: Programming Language :: Python :: 3.8
Classifier: Programming Language :: Python :: 3.9
Classifier: Framework :: Django :: 3.1
Classifier: Framework :: Celery
Classifier: License :: OSI Approved :: MIT License
Classifier: Operating System :: OS Independent
Requires-Python: >=3.6
License-File: LICENSE
Requires-Dist: Django (>=3.1)
Requires-Dist: celery (>=5.0.0)
Requires-Dist: django-import-export (>=2.2.0)
